data.py
orchest-0.0.2.dist-info/LICENSE
orchest-0.0.2.dist-info/METADATA
orchest-0.0.2.dist-info/WHEEL
orchest-0.0.2.dist-info/top_level.txt
orchest-0.0.2.dist-info/RECORD
